README.md
setup.py
gh_views/__init__.py
gh_views/main.py
gh_views.egg-info/PKG-INFO
gh_views.egg-info/SOURCES.txt
gh_views.egg-info/dependency_links.txt
gh_views.egg-info/entry_points.txt
gh_views.egg-info/top_level.txt