Metadata-Version: 2.1
Name: gh-views
Version: 3.1.0
Home-page: https://github.com/talwrii/gh-views
Author: @readwithai
Author-email: talwrii@gmail.com
License: BSD
Keywords: github,statistics
